jaxnuts/__init__.py
jaxnuts/sampler.py
jaxnuts-0.0.1.dist-info/LICENSE.txt
jaxnuts-0.0.1.dist-info/METADATA
jaxnuts-0.0.1.dist-info/WHEEL
jaxnuts-0.0.1.dist-info/top_level.txt
jaxnuts-0.0.1.dist-info/RECORD
