Metadata-Version: 2.1
Name: jaxnuts
Version: 0.0.1
Summary: Python implementation of the No-U-Turn Sampler
Home-page: https://github.com/guillaume-plc/jaxnuts
Author: Guillaume Planchon
Author-email: gp.planchon@gmail.com
License: UNKNOWN
Project-URL: Bug Tracker, https://github.com/guillaume-plc/jaxnuts/issues
Platform: UNKNOWN
Classifier: Programming Language :: Python :: 3
Classifier: License :: OSI Approved :: MIT License
Classifier: Operating System :: OS Independent
Requires-Python: >=3.8
License-File: LICENSE.txt
